Metadata-Version: 1.0
Name: omuliga-probability
Version: 0.1
Summary: Gaussian and Binomial distributions
Home-page: UNKNOWN
Author: Olivia Nabbosa
Author-email: olivia.nabbosa@outlook.com
License: UNKNOWN
Platform: UNKNOWN
